dynamax/__init__.py
dynamax/_version.py
dynamax/parameters.py
dynamax/parameters_test.py
dynamax/ssm.py
dynamax/types.py
dynamax/warnings.py
dynamax/generalized_gaussian_ssm/__init__.py
dynamax/generalized_gaussian_ssm/inference.py
dynamax/generalized_gaussian_ssm/inference_test.py
dynamax/generalized_gaussian_ssm/models.py
dynamax/generalized_gaussian_ssm/models_test.py
dynamax/generalized_gaussian_ssm/demos/__init__.py
dynamax/generalized_gaussian_ssm/demos/cmgf_logreg_estimator.py
dynamax/hidden_markov_model/__init__.py
dynamax/hidden_markov_model/inference.py
dynamax/hidden_markov_model/inference_test.py
dynamax/hidden_markov_model/parallel_inference.py
dynamax/hidden_markov_model/demos/categorical_glm_hmm_demo.py
dynamax/hidden_markov_model/demos/poisson_hmm_earthquakes.py
dynamax/hidden_markov_model/models/__init__.py
dynamax/hidden_markov_model/models/abstractions.py
dynamax/hidden_markov_model/models/arhmm.py
dynamax/hidden_markov_model/models/bernoulli_hmm.py
dynamax/hidden_markov_model/models/categorical_glm_hmm.py
dynamax/hidden_markov_model/models/categorical_hmm.py
dynamax/hidden_markov_model/models/gamma_hmm.py
dynamax/hidden_markov_model/models/gaussian_hmm.py
dynamax/hidden_markov_model/models/gmm_hmm.py
dynamax/hidden_markov_model/models/initial.py
dynamax/hidden_markov_model/models/linreg_hmm.py
dynamax/hidden_markov_model/models/logreg_hmm.py
dynamax/hidden_markov_model/models/multinomial_hmm.py
dynamax/hidden_markov_model/models/poisson_hmm.py
dynamax/hidden_markov_model/models/test_models.py
dynamax/hidden_markov_model/models/transitions.py
dynamax/linear_gaussian_ssm/__init__.py
dynamax/linear_gaussian_ssm/inference.py
dynamax/linear_gaussian_ssm/inference_test.py
dynamax/linear_gaussian_ssm/info_inference.py
dynamax/linear_gaussian_ssm/info_inference_test.py
dynamax/linear_gaussian_ssm/models.py
dynamax/linear_gaussian_ssm/models_test.py
dynamax/linear_gaussian_ssm/parallel_inference.py
dynamax/linear_gaussian_ssm/parallel_inference_test.py
dynamax-1.0.1.dist-info/licenses/LICENSE
dynamax-1.0.1.dist-info/METADATA
dynamax-1.0.1.dist-info/WHEEL
dynamax-1.0.1.dist-info/top_level.txt
dynamax-1.0.1.dist-info/RECORD
