Metadata-Version: 2.4
Name: dynamax
Version: 1.0.1
Summary: Dynamic State Space Models in JAX.
Author: Scott Linderman, Peter Chang, Giles Harper-Donnelly, Aleyna Kara, Xinglong Li, Kevin Murphy
Maintainer-email: Scott Linderman <scott.linderman@stanford.edu>
License: MIT License
Project-URL: homepage, https://github.com/probml/dynamax
Project-URL: documentation, https://probml.github.io/dynamax/
Project-URL: repository, https://github.com/probml/dynamax
Classifier: Programming Language :: Python
Requires-Python: >=3.10
License-File: LICENSE
Requires-Dist: jax>=0.3.15
Requires-Dist: jaxlib
Requires-Dist: fastprogress
Requires-Dist: optax
Requires-Dist: tensorflow_probability
Requires-Dist: scikit-learn
Requires-Dist: jaxtyping
Requires-Dist: typing-extensions
Requires-Dist: numpy
Provides-Extra: notebooks
Requires-Dist: matplotlib; extra == "notebooks"
Requires-Dist: seaborn; extra == "notebooks"
Requires-Dist: flax; extra == "notebooks"
Requires-Dist: blackjax; extra == "notebooks"
Requires-Dist: graphviz; extra == "notebooks"
Requires-Dist: scipy; extra == "notebooks"
Provides-Extra: doc
Requires-Dist: matplotlib; extra == "doc"
Requires-Dist: seaborn; extra == "doc"
Requires-Dist: flax; extra == "doc"
Requires-Dist: blackjax; extra == "doc"
Requires-Dist: graphviz; extra == "doc"
Requires-Dist: scipy; extra == "doc"
Requires-Dist: sphinx; extra == "doc"
Requires-Dist: sphinx-autobuild; extra == "doc"
Requires-Dist: sphinx_autodoc_typehints; extra == "doc"
Requires-Dist: sphinx-math-dollar; extra == "doc"
Requires-Dist: myst-nb; extra == "doc"
Requires-Dist: jupytext; extra == "doc"
Requires-Dist: sphinx-book-theme; extra == "doc"
Provides-Extra: test
Requires-Dist: codecov; extra == "test"
Requires-Dist: coverage; extra == "test"
Requires-Dist: pytest>=3.9; extra == "test"
Requires-Dist: pytest-cov; extra == "test"
Requires-Dist: interrogate>=1.5.0; extra == "test"
Provides-Extra: dev
Requires-Dist: matplotlib; extra == "dev"
Requires-Dist: seaborn; extra == "dev"
Requires-Dist: flax; extra == "dev"
Requires-Dist: blackjax; extra == "dev"
Requires-Dist: graphviz; extra == "dev"
Requires-Dist: scipy; extra == "dev"
Requires-Dist: sphinx; extra == "dev"
Requires-Dist: sphinx-autobuild; extra == "dev"
Requires-Dist: sphinx_autodoc_typehints; extra == "dev"
Requires-Dist: sphinx-math-dollar; extra == "dev"
Requires-Dist: myst-nb; extra == "dev"
Requires-Dist: jupytext; extra == "dev"
Requires-Dist: sphinx-book-theme; extra == "dev"
Requires-Dist: codecov; extra == "dev"
Requires-Dist: coverage; extra == "dev"
Requires-Dist: pytest>=3.9; extra == "dev"
Requires-Dist: pytest-cov; extra == "dev"
Requires-Dist: interrogate>=1.5.0; extra == "dev"
Dynamic: license-file
